{
    "GeneralInformation": {
        "DatasetName": "HadCRUT5",
        "DatasetVersion": "",
        "DatasetLink": "",
        "AssessorName": "John Pill",
        "AssessorEmailAddress": "john.pill@metoffice.gov.uk",
        "RawOrDerived": "",
        "ObservedModeledSyntheticData": "",
        "DataSource": ""
    },
    "DataQuality": {
        "WillBeUpdated": null,
        "WhenNewDataAdded": null,
        "DifferentStages": null,
        "DelayBetweenStages": "",
        "SupersedeCurrentVersion": null,
        "DocumentationAvailable": null,
        "LinkToReport": "",
        "SpatialCoverage": null,
        "TemporalCoverage": null,
        "SelfConsistent": null,
        "ConsistentWithSimilarData": null,
        "MonitoringProcessesExist": null,
        "MonitoringProcessesDetails": "",
        "KnownBias": null,
        "BiasExamined": null,
        "BiasMeasures": "",
        "MetrologicalTraceability": "",
        "BiasReport": null,
        "ReportedBias": null,
        "BiasReportLink": "",
        "BiasReductionToolsLink": "",
        "BiasCorrectedDatasetLink": "",
        "QuantitativeResolutionInfo": null,
        "PublishedQualityProcedures": null,
        "QualityInformationLink": "",
        "ProvenanceTracked": null,
        "DataIntegrityChecks": null,
        "DatasetVolume": "",
        "DatasetDimensions": 0,
        "DatasetNumFiles": 0,
        "DatasetNumRows": 0,
        "DatasetNumImages": 0,
        "DatasetImageSize": ""
    },
    "DataDocumentation": {
        "MetadataStandard": null,
        "MetadataStandardName": null,
        "MetadataMachineReadable": null,
        "MetadataSpatialTemporalExtent": null,
        "DataDictionaryExists": null,
        "DataDictionaryStandardised": null,
        "DataDictionaryMachineReadable": null,
        "DataDictionaryParametersFollowStandard": null,
        "DataDictionaryStandardName": "",
        "DataDictionaryParametersCrosswalked": null,
        "IdentifierExists": null,
        "Identifier": "",
        "ContactInformation": null,
        "UserFeedbackMechanism": null,
        "ExampleCodesAvailable": null,
        "LicenseType": "",
        "LicenceMachineReadable": null,
        "UsedInAIorMLReports": "",
        "UsageRecommendations": null
    },
    "DataAccess": {
        "FileFormats": [],
        "FileFormatsMachineReadable": null,
        "OpenFormatAvailable": null,
        "FormatConversionTools": null,
        "ConversionToolsLink": "",
        "AuthenticationRequired": null,
        "DirectDownloadAvailable": null,
        "APIorWebAvailable": null,
        "APIOpenStandard": null,
        "APIDocumentation": null,
        "APIDocumentationLink": "",
        "SecurityMeasuresTaken": null,
        "DataAggregated": null,
        "DataAnonymized": null,
        "SecureAccessForAuthorizedUsers": null
    },
    "DataPreparation": {
        "NullValuesFilled": null,
        "OutliersIdentified": null,
        "Gridded": null,
        "TransformedFromOriginal": null,
        "OriginalSamplingAvailable": null,
        "SupervisedLearningLabels": null,
        "SupervisedLearningLabelStandards": ""
    }
}